LICENSE
README.md
setup.cfg
setup.py
cnlp/__init__.py
cnlp/dimensionality_reduction_methods.py
cnlp/probabilistic_methods.py
cnlp/utils.py
cnlp/other_methods/__init__.py
cnlp/other_methods/information_theory.py
cnlp/similarity_methods/__init__.py
cnlp/similarity_methods/global_similarity.py
cnlp/similarity_methods/local_similarity.py
cnlp/similarity_methods/quasi_local_similarity.py
complex_network_link_prediction.egg-info/PKG-INFO
complex_network_link_prediction.egg-info/SOURCES.txt
complex_network_link_prediction.egg-info/dependency_links.txt
complex_network_link_prediction.egg-info/requires.txt
complex_network_link_prediction.egg-info/top_level.txt