Metadata-Version: 2.1
Name: complex-network-link-prediction
Version: 1.3
Summary: A python library for link prediction in social networks
Home-page: https://github.com/Typing-Monkeys/social-network-link-prediction
Author: Cristian Cosci, Fabrizio Fagiolo, Nicolò Vescera, Nicolò Posta, Tommaso Romani
License: MIT
Keywords: Link Prediction,Social Network,Complex Network Analisys
License-File: LICENSE
